prop2po/__init__.py
prop2po/main.py
prop2po-1.1.0.dist-info/LICENSE
prop2po-1.1.0.dist-info/METADATA
prop2po-1.1.0.dist-info/WHEEL
prop2po-1.1.0.dist-info/entry_points.txt
prop2po-1.1.0.dist-info/top_level.txt
prop2po-1.1.0.dist-info/RECORD
