Metadata-Version: 2.1
Name: prop2po
Version: 1.1.0
Summary: Package converting java property file to Gettext PO
Home-page: https://github.com/mivek/prop2po
Author: Jean-Kevin KPADEY
Author-email: jeankevin.kpadey@gmail.com
Project-URL: Bug Tracker, https://github.com/mivek/prop2po/issues
Classifier: Programming Language :: Python :: 3
Classifier: License :: OSI Approved :: MIT License
Classifier: Operating System :: OS Independent
Requires-Python: >=3.8
License-File: LICENSE
Requires-Dist: Click
